[
  {
    "_id": "158393297483727762:1496601005000",
    "refid": "b3ce2dd9-e7bd-4515-af1d-dc8bfb47ed03",
    "timestamp": 1496601005000,
    "tracker_id": "151704003336602618",
    "vehicle_id": "158393297483727762",
    "sp": 92.72,
    "hd": 137.85,
    "exb": 1,
    "account_id": "149089795410363018",
    "battery": 100,
    "battery_str": 0,
    "dist_sp": 260.194458,
    "multi_geo": [
      {
        "geocode": {
          "lat": 15.528818333333334,
          "lng": 74.90577333333333,
          "fix": 3
        }
      },
      {
        "geocode": {
          "lat": 15.528733333333333,
          "lng": 74.906,
          "fix": 3
        }
      },
      {
        "geocode": {
          "lat": 15.528643333333333,
          "lng": 74.90622666666667,
          "fix": 3
        }
      },
      {
        "geocode": {
          "lat": 15.52854,
          "lng": 74.90645,
          "fix": 3
        }
      },
      {
        "geocode": {
          "lat": 15.528425,
          "lng": 74.90666833333333,
          "fix": 3
        }
      },
      {
        "geocode": {
          "lat": 15.528298333333334,
          "lng": 74.90687666666666,
          "fix": 3
        }
      },
      {
        "geocode": {
          "lat": 15.528158333333334,
          "lng": 74.90707,
          "fix": 3
        }
      },
      {
        "geocode": {
          "lat": 15.528006666666666,
          "lng": 74.90725,
          "fix": 3
        }
      },
      {
        "geocode": {
          "lat": 15.527846666666667,
          "lng": 74.90742666666667,
          "fix": 3
        }
      },
      {
        "geocode": {
          "lat": 15.527665,
          "lng": 74.907585,
          "fix": 3
        }
      }
    ],
    "multi_sp": [
      {
        "sp": 93.11
      },
      {
        "sp": 93.97
      },
      {
        "sp": 94
      },
      {
        "sp": 95.98
      },
      {
        "sp": 94.83
      },
      {
        "sp": 94
      },
      {
        "sp": 92.61
      },
      {
        "sp": 92.74
      },
      {
        "sp": 92.74
      },
      {
        "sp": 92.72
      }
    ],
    "loc": {
      "type": "Point",
      "coordinates": [
        15.527665,
        74.907585
      ]
    },
    "fix": 3
  },
  {
    "_id": "158393297483727762:1496601015000",
    "refid": "c00fd753-6d6d-45d4-90af-543025dbeb80",
    "timestamp": 1496601015000,
    "tracker_id": "151704003336602618",
    "vehicle_id": "158393297483727762",
    "sp": 93.45,
    "account_id": "149089795410363018",
    "loc": {
      "type": "Point",
      "coordinates": [
        15.525551666666667,
        74.90851333333333
      ]
    },
    "fix": 3
  },
  {
    "_id": "158393297483727762:1496601016000",
    "refid": "2a7611bd-28ce-4cf3-8578-2b0431cce721",
    "timestamp": 1496601016000,
    "tracker_id": "151704003336602618",
    "vehicle_id": "158393297483727762",
    "sp": 92.29,
    "hd": 158.71,
    "exb": 1,
    "account_id": "149089795410363018",
    "battery": 100,
    "battery_str": 0,
    "dist_sp": 253.766663,
    "multi_geo": [
      {
        "geocode": {
          "lat": 15.527286666666667,
          "lng": 74.907835,
          "fix": 3
        }
      },
      {
        "geocode": {
          "lat": 15.52709,
          "lng": 74.90794166666667,
          "fix": 3
        }
      },
      {
        "geocode": {
          "lat": 15.526885,
          "lng": 74.90802,
          "fix": 3
        }
      },
      {
        "geocode": {
          "lat": 15.526671666666667,
          "lng": 74.908105,
          "fix": 3
        }
      },
      {
        "geocode": {
          "lat": 15.526456666666666,
          "lng": 74.90818666666667,
          "fix": 3
        }
      },
      {
        "geocode": {
          "lat": 15.526231666666666,
          "lng": 74.90826833333334,
          "fix": 3
        }
      },
      {
        "geocode": {
          "lat": 15.526005,
          "lng": 74.90835,
          "fix": 3
        }
      },
      {
        "geocode": {
          "lat": 15.525778333333333,
          "lng": 74.90843166666667,
          "fix": 3
        }
      },
      {
        "geocode": {
          "lat": 15.525551666666667,
          "lng": 74.90851333333333,
          "fix": 3
        }
      },
      {
        "geocode": {
          "lat": 15.525326666666666,
          "lng": 74.90859166666667,
          "fix": 3
        }
      }
    ],
    "multi_sp": [
      {
        "sp": 90.04
      },
      {
        "sp": 89.16
      },
      {
        "sp": 89.65
      },
      {
        "sp": 90.4
      },
      {
        "sp": 90.4
      },
      {
        "sp": 92.23
      },
      {
        "sp": 92.53
      },
      {
        "sp": 93.41
      },
      {
        "sp": 93.45
      },
      {
        "sp": 92.29
      }
    ],
    "loc": {
      "type": "Point",
      "coordinates": [
        15.525326666666666,
        74.90859166666667
      ]
    },
    "fix": 3
  },
  {
    "_id": "158393297483727762:1496601027000",
    "refid": "ebb9a03a-37a4-4588-8655-cda964a29807",
    "timestamp": 1496601027000,
    "tracker_id": "151704003336602618",
    "vehicle_id": "158393297483727762",
    "sp": 89.8,
    "hd": 129.07,
    "exb": 1,
    "account_id": "149089795410363018",
    "battery": 100,
    "battery_str": 0,
    "dist_sp": 253.419449,
    "multi_geo": [
      {
        "geocode": {
          "lat": 15.52488,
          "lng": 74.90876,
          "fix": 3
        }
      },
      {
        "geocode": {
          "lat": 15.524665,
          "lng": 74.90885833333333,
          "fix": 3
        }
      },
      {
        "geocode": {
          "lat": 15.524458333333333,
          "lng": 74.90896833333333,
          "fix": 3
        }
      },
      {
        "geocode": {
          "lat": 15.524256666666666,
          "lng": 74.90908833333333,
          "fix": 3
        }
      },
      {
        "geocode": {
          "lat": 15.524061666666666,
          "lng": 74.90921666666667,
          "fix": 3
        }
      },
      {
        "geocode": {
          "lat": 15.523881666666666,
          "lng": 74.90935833333333,
          "fix": 3
        }
      },
      {
        "geocode": {
          "lat": 15.523703333333334,
          "lng": 74.90950833333333,
          "fix": 3
        }
      },
      {
        "geocode": {
          "lat": 15.523535,
          "lng": 74.90967166666667,
          "fix": 3
        }
      },
      {
        "geocode": {
          "lat": 15.52338,
          "lng": 74.909845,
          "fix": 3
        }
      },
      {
        "geocode": {
          "lat": 15.523238333333333,
          "lng": 74.91002666666667,
          "fix": 3
        }
      }
    ],
    "multi_sp": [
      {
        "sp": 92.73
      },
      {
        "sp": 91.56
      },
      {
        "sp": 91.43
      },
      {
        "sp": 91.91
      },
      {
        "sp": 91.9
      },
      {
        "sp": 90.92
      },
      {
        "sp": 90.48
      },
      {
        "sp": 91.09
      },
      {
        "sp": 90.49
      },
      {
        "sp": 89.8
      }
    ],
    "loc": {
      "type": "Point",
      "coordinates": [
        15.523238333333333,
        74.91002666666667
      ]
    },
    "fix": 3
  },
  {
    "_id": "158393297483727762:1496601038000",
    "refid": "74490320-6489-4062-a383-97e1a214a396",
    "timestamp": 1496601038000,
    "tracker_id": "151704003336602618",
    "vehicle_id": "158393297483727762",
    "sp": 85.96,
    "hd": 120.51,
    "exb": 1,
    "account_id": "149089795410363018",
    "battery": 100,
    "battery_str": 0,
    "dist_sp": 239.436111,
    "multi_geo": [
      {
        "geocode": {
          "lat": 15.522993333333334,
          "lng": 74.91041166666666,
          "fix": 3
        }
      },
      {
        "geocode": {
          "lat": 15.522878333333333,
          "lng": 74.91060833333333,
          "fix": 3
        }
      },
      {
        "geocode": {
          "lat": 15.522766666666667,
          "lng": 74.910805,
          "fix": 3
        }
      },
      {
        "geocode": {
          "lat": 15.522656666666666,
          "lng": 74.911,
          "fix": 3
        }
      },
      {
        "geocode": {
          "lat": 15.522546666666667,
          "lng": 74.91119333333333,
          "fix": 3
        }
      },
      {
        "geocode": {
          "lat": 15.522438333333334,
          "lng": 74.91138833333333,
          "fix": 3
        }
      },
      {
        "geocode": {
          "lat": 15.522331666666666,
          "lng": 74.91157666666666,
          "fix": 3
        }
      },
      {
        "geocode": {
          "lat": 15.522223333333333,
          "lng": 74.91176666666667,
          "fix": 3
        }
      },
      {
        "geocode": {
          "lat": 15.522116666666667,
          "lng": 74.91196,
          "fix": 3
        }
      },
      {
        "geocode": {
          "lat": 15.522008333333334,
          "lng": 74.91215166666667,
          "fix": 3
        }
      }
    ],
    "multi_sp": [
      {
        "sp": 88.21
      },
      {
        "sp": 87.38
      },
      {
        "sp": 87.28
      },
      {
        "sp": 87.17
      },
      {
        "sp": 86.13
      },
      {
        "sp": 85.27
      },
      {
        "sp": 84.79
      },
      {
        "sp": 84.83
      },
      {
        "sp": 84.95
      },
      {
        "sp": 85.96
      }
    ],
    "loc": {
      "type": "Point",
      "coordinates": [
        15.522008333333334,
        74.91215166666667
      ]
    },
    "fix": 3
  },
  {
    "_id": "158393297483727762:1496601050000",
    "refid": "b9fca0cb-887e-4c30-9df8-b45b34eee203",
    "timestamp": 1496601050000,
    "tracker_id": "151704003336602618",
    "vehicle_id": "158393297483727762",
    "sp": 90.91,
    "hd": 119.89,
    "exb": 1,
    "account_id": "149089795410363018",
    "battery": 100,
    "battery_str": 0,
    "dist_sp": 247.866669,
    "multi_geo": [
      {
        "geocode": {
          "lat": 15.521673333333334,
          "lng": 74.91273,
          "fix": 3
        }
      },
      {
        "geocode": {
          "lat": 15.521561666666667,
          "lng": 74.91292666666666,
          "fix": 3
        }
      },
      {
        "geocode": {
          "lat": 15.521451666666668,
          "lng": 74.91312833333333,
          "fix": 3
        }
      },
      {
        "geocode": {
          "lat": 15.521338333333333,
          "lng": 74.91333,
          "fix": 3
        }
      },
      {
        "geocode": {
          "lat": 15.521226666666667,
          "lng": 74.91353166666667,
          "fix": 3
        }
      },
      {
        "geocode": {
          "lat": 15.521115,
          "lng": 74.913735,
          "fix": 3
        }
      },
      {
        "geocode": {
          "lat": 15.521001666666667,
          "lng": 74.91393833333333,
          "fix": 3
        }
      },
      {
        "geocode": {
          "lat": 15.520886666666666,
          "lng": 74.91414333333333,
          "fix": 3
        }
      },
      {
        "geocode": {
          "lat": 15.520771666666667,
          "lng": 74.91435,
          "fix": 3
        }
      },
      {
        "geocode": {
          "lat": 15.520658333333333,
          "lng": 74.91455666666667,
          "fix": 3
        }
      }
    ],
    "multi_sp": [
      {
        "sp": 86.81
      },
      {
        "sp": 87.84
      },
      {
        "sp": 87.93
      },
      {
        "sp": 88.63
      },
      {
        "sp": 89.05
      },
      {
        "sp": 89.1
      },
      {
        "sp": 90.11
      },
      {
        "sp": 90.68
      },
      {
        "sp": 91.26
      },
      {
        "sp": 90.91
      }
    ],
    "loc": {
      "type": "Point",
      "coordinates": [
        15.520658333333333,
        74.91455666666667
      ]
    },
    "fix": 3
  },
  {
    "_id": "158393297483727762:1496601053000",
    "refid": "97fd340e-3f27-40ad-9e8f-5525717c8e4d",
    "timestamp": 1496601053000,
    "tracker_id": "151704003336602618",
    "vehicle_id": "158393297483727762",
    "sp": 92.09,
    "account_id": "149089795410363018",
    "loc": {
      "type": "Point",
      "coordinates": [
        15.520325,
        74.91519833333334
      ]
    },
    "fix": 3
  },
  {
    "_id": "158393297483727762:1496601061000",
    "refid": "63fd3592-282f-47d6-ba51-22ea0aa6af7f",
    "timestamp": 1496601061000,
    "tracker_id": "151704003336602618",
    "vehicle_id": "158393297483727762",
    "sp": 89.56,
    "hd": 109.8,
    "exb": 1,
    "account_id": "149089795410363018",
    "battery": 100,
    "battery_str": 0,
    "dist_sp": 252.547226,
    "multi_geo": [
      {
        "geocode": {
          "lat": 15.520433333333333,
          "lng": 74.91498333333334,
          "fix": 3
        }
      },
      {
        "geocode": {
          "lat": 15.520325,
          "lng": 74.91519833333334,
          "fix": 3
        }
      },
      {
        "geocode": {
          "lat": 15.520221666666666,
          "lng": 74.91541833333333,
          "fix": 3
        }
      },
      {
        "geocode": {
          "lat": 15.52012,
          "lng": 74.91563666666667,
          "fix": 3
        }
      },
      {
        "geocode": {
          "lat": 15.520021666666667,
          "lng": 74.91585333333333,
          "fix": 3
        }
      },
      {
        "geocode": {
          "lat": 15.519933333333334,
          "lng": 74.91607333333333,
          "fix": 3
        }
      },
      {
        "geocode": {
          "lat": 15.51985,
          "lng": 74.91629333333333,
          "fix": 3
        }
      },
      {
        "geocode": {
          "lat": 15.519783333333333,
          "lng": 74.91652333333333,
          "fix": 3
        }
      },
      {
        "geocode": {
          "lat": 15.519708333333334,
          "lng": 74.91674333333333,
          "fix": 3
        }
      },
      {
        "geocode": {
          "lat": 15.51963,
          "lng": 74.916965,
          "fix": 3
        }
      }
    ],
    "multi_sp": [
      {
        "sp": 92.13
      },
      {
        "sp": 92.09
      },
      {
        "sp": 92.64
      },
      {
        "sp": 91.8
      },
      {
        "sp": 91.71
      },
      {
        "sp": 89.95
      },
      {
        "sp": 89.9
      },
      {
        "sp": 89.86
      },
      {
        "sp": 89.53
      },
      {
        "sp": 89.56
      }
    ],
    "loc": {
      "type": "Point",
      "coordinates": [
        15.51963,
        74.916965
      ]
    },
    "fix": 3
  },
  {
    "_id": "158393297483727762:1496601072000",
    "refid": "8ec2197f-e050-448d-bdf1-a790cf473a69",
    "timestamp": 1496601072000,
    "tracker_id": "151704003336602618",
    "vehicle_id": "158393297483727762",
    "sp": 92.92,
    "hd": 108.55,
    "exb": 1,
    "account_id": "149089795410363018",
    "battery": 100,
    "battery_str": 0,
    "dist_sp": 252.841675,
    "multi_geo": [
      {
        "geocode": {
          "lat": 15.519478333333334,
          "lng": 74.917405,
          "fix": 3
        }
      },
      {
        "geocode": {
          "lat": 15.519403333333333,
          "lng": 74.91762333333334,
          "fix": 3
        }
      },
      {
        "geocode": {
          "lat": 15.519328333333334,
          "lng": 74.91784166666666,
          "fix": 3
        }
      },
      {
        "geocode": {
          "lat": 15.519256666666667,
          "lng": 74.91806333333334,
          "fix": 3
        }
      },
      {
        "geocode": {
          "lat": 15.519181666666666,
          "lng": 74.91828666666666,
          "fix": 3
        }
      },
      {
        "geocode": {
          "lat": 15.519108333333334,
          "lng": 74.91851,
          "fix": 3
        }
      },
      {
        "geocode": {
          "lat": 15.519031666666667,
          "lng": 74.918735,
          "fix": 3
        }
      },
      {
        "geocode": {
          "lat": 15.518956666666666,
          "lng": 74.91896,
          "fix": 3
        }
      },
      {
        "geocode": {
          "lat": 15.518881666666667,
          "lng": 74.91918666666666,
          "fix": 3
        }
      },
      {
        "geocode": {
          "lat": 15.518805,
          "lng": 74.91941333333334,
          "fix": 3
        }
      }
    ],
    "multi_sp": [
      {
        "sp": 89.31
      },
      {
        "sp": 88.86
      },
      {
        "sp": 89.47
      },
      {
        "sp": 90.68
      },
      {
        "sp": 90.68
      },
      {
        "sp": 91.24
      },
      {
        "sp": 91.77
      },
      {
        "sp": 92.43
      },
      {
        "sp": 92.87
      },
      {
        "sp": 92.92
      }
    ],
    "loc": {
      "type": "Point",
      "coordinates": [
        15.518805,
        74.91941333333334
      ]
    },
    "fix": 3
  },
  {
    "_id": "158393297483727762:1496601072000",
    "refid": "8ec2197f-e050-448d-bdf1-a790cf473a69",
    "timestamp": 1496601072000,
    "tracker_id": "151704003336602618",
    "vehicle_id": "158393297483727762",
    "sp": 92.92,
    "hd": 108.55,
    "exb": 1,
    "account_id": "149089795410363018",
    "battery": 100,
    "battery_str": 0,
    "dist_sp": 252.841675,
    "multi_geo": [
      {
        "geocode": {
          "lat": 15.519478333333334,
          "lng": 74.917405,
          "fix": 3
        }
      },
      {
        "geocode": {
          "lat": 15.519403333333333,
          "lng": 74.91762333333334,
          "fix": 3
        }
      },
      {
        "geocode": {
          "lat": 15.519328333333334,
          "lng": 74.91784166666666,
          "fix": 3
        }
      },
      {
        "geocode": {
          "lat": 15.519256666666667,
          "lng": 74.91806333333334,
          "fix": 3
        }
      },
      {
        "geocode": {
          "lat": 15.519181666666666,
          "lng": 74.91828666666666,
          "fix": 3
        }
      },
      {
        "geocode": {
          "lat": 15.519108333333334,
          "lng": 74.91851,
          "fix": 3
        }
      },
      {
        "geocode": {
          "lat": 15.519031666666667,
          "lng": 74.918735,
          "fix": 3
        }
      },
      {
        "geocode": {
          "lat": 15.518956666666666,
          "lng": 74.91896,
          "fix": 3
        }
      },
      {
        "geocode": {
          "lat": 15.518881666666667,
          "lng": 74.91918666666666,
          "fix": 3
        }
      },
      {
        "geocode": {
          "lat": 15.518805,
          "lng": 74.91941333333334,
          "fix": 3
        }
      }
    ],
    "multi_sp": [
      {
        "sp": 89.31
      },
      {
        "sp": 88.86
      },
      {
        "sp": 89.47
      },
      {
        "sp": 90.68
      },
      {
        "sp": 90.68
      },
      {
        "sp": 91.24
      },
      {
        "sp": 91.77
      },
      {
        "sp": 92.43
      },
      {
        "sp": 92.87
      },
      {
        "sp": 92.92
      }
    ],
    "loc": {
      "type": "Point",
      "coordinates": [
        15.518805,
        74.91941333333334
      ]
    },
    "fix": 3
  },
  {
    "_id": "158393297483727762:1496601083000",
    "refid": "e606e609-6d43-4f92-aa9f-4435a7e2e173",
    "timestamp": 1496601083000,
    "tracker_id": "151704003336602618",
    "vehicle_id": "158393297483727762",
    "sp": 90.01,
    "hd": 109.95,
    "exb": 1,
    "account_id": "149089795410363018",
    "battery": 100,
    "battery_str": 0,
    "dist_sp": 252.09166,
    "multi_geo": [
      {
        "geocode": {
          "lat": 15.518655,
          "lng": 74.91986666666666,
          "fix": 3
        }
      },
      {
        "geocode": {
          "lat": 15.51858,
          "lng": 74.92009166666666,
          "fix": 3
        }
      },
      {
        "geocode": {
          "lat": 15.518506666666667,
          "lng": 74.920315,
          "fix": 3
        }
      },
      {
        "geocode": {
          "lat": 15.518431666666666,
          "lng": 74.92053666666666,
          "fix": 3
        }
      },
      {
        "geocode": {
          "lat": 15.518355,
          "lng": 74.92075833333334,
          "fix": 3
        }
      },
      {
        "geocode": {
          "lat": 15.518278333333333,
          "lng": 74.92098,
          "fix": 3
        }
      },
      {
        "geocode": {
          "lat": 15.518201666666666,
          "lng": 74.9212,
          "fix": 3
        }
      },
      {
        "geocode": {
          "lat": 15.518128333333333,
          "lng": 74.92142,
          "fix": 3
        }
      },
      {
        "geocode": {
          "lat": 15.51805,
          "lng": 74.92163833333333,
          "fix": 3
        }
      },
      {
        "geocode": {
          "lat": 15.517975,
          "lng": 74.92185666666667,
          "fix": 3
        }
      }
    ],
    "multi_sp": [
      {
        "sp": 92.33
      },
      {
        "sp": 91.85
      },
      {
        "sp": 91.3
      },
      {
        "sp": 90.85
      },
      {
        "sp": 90.83
      },
      {
        "sp": 90.76
      },
      {
        "sp": 90.21
      },
      {
        "sp": 89.4
      },
      {
        "sp": 89.99
      },
      {
        "sp": 90.01
      }
    ],
    "loc": {
      "type": "Point",
      "coordinates": [
        15.517975,
        74.92185666666667
      ]
    },
    "fix": 3
  },
  {
    "_id": "158393297483727762:1496601094000",
    "refid": "b959ecc7-ffe9-4863-a705-12124e5fec4d",
    "timestamp": 1496601094000,
    "tracker_id": "151704003336602618",
    "vehicle_id": "158393297483727762",
    "sp": 84.09,
    "hd": 108.66,
    "exb": 1,
    "account_id": "149089795410363018",
    "battery": 100,
    "battery_str": 0,
    "dist_sp": 239.580551,
    "multi_geo": [
      {
        "geocode": {
          "lat": 15.517826666666666,
          "lng": 74.92228666666666,
          "fix": 3
        }
      },
      {
        "geocode": {
          "lat": 15.517753333333333,
          "lng": 74.9225,
          "fix": 3
        }
      },
      {
        "geocode": {
          "lat": 15.517678333333333,
          "lng": 74.92271,
          "fix": 3
        }
      },
      {
        "geocode": {
          "lat": 15.517603333333334,
          "lng": 74.92292166666667,
          "fix": 3
        }
      },
      {
        "geocode": {
          "lat": 15.517528333333333,
          "lng": 74.92313166666666,
          "fix": 3
        }
      },
      {
        "geocode": {
          "lat": 15.517456666666666,
          "lng": 74.92334166666667,
          "fix": 3
        }
      },
      {
        "geocode": {
          "lat": 15.517385,
          "lng": 74.92354833333333,
          "fix": 3
        }
      },
      {
        "geocode": {
          "lat": 15.517316666666666,
          "lng": 74.92375666666666,
          "fix": 3
        }
      },
      {
        "geocode": {
          "lat": 15.51725,
          "lng": 74.92396166666667,
          "fix": 3
        }
      },
      {
        "geocode": {
          "lat": 15.517183333333334,
          "lng": 74.92416833333333,
          "fix": 3
        }
      }
    ],
    "multi_sp": [
      {
        "sp": 88.39
      },
      {
        "sp": 87.79
      },
      {
        "sp": 86.92
      },
      {
        "sp": 87.23
      },
      {
        "sp": 87.12
      },
      {
        "sp": 86.45
      },
      {
        "sp": 85.55
      },
      {
        "sp": 84.91
      },
      {
        "sp": 84.04
      },
      {
        "sp": 84.09
      }
    ],
    "loc": {
      "type": "Point",
      "coordinates": [
        15.517183333333334,
        74.92416833333333
      ]
    },
    "fix": 3
  },
  {
    "_id": "158393297483727762:1496601105000",
    "refid": "c921599e-bc63-4bf4-813a-c134fe46cc91",
    "timestamp": 1496601105000,
    "tracker_id": "151704003336602618",
    "vehicle_id": "158393297483727762",
    "sp": 80.78,
    "hd": 99.02,
    "exb": 1,
    "account_id": "149089795410363018",
    "battery": 100,
    "battery_str": 0,
    "dist_sp": 223.780563,
    "multi_geo": [
      {
        "geocode": {
          "lat": 15.517056666666667,
          "lng": 74.92457,
          "fix": 3
        }
      },
      {
        "geocode": {
          "lat": 15.517001666666667,
          "lng": 74.92478166666666,
          "fix": 3
        }
      },
      {
        "geocode": {
          "lat": 15.516953333333333,
          "lng": 74.92499166666667,
          "fix": 3
        }
      },
      {
        "geocode": {
          "lat": 15.516911666666667,
          "lng": 74.92519833333333,
          "fix": 3
        }
      },
      {
        "geocode": {
          "lat": 15.516871666666667,
          "lng": 74.92540333333334,
          "fix": 3
        }
      },
      {
        "geocode": {
          "lat": 15.516835,
          "lng": 74.9256,
          "fix": 3
        }
      },
      {
        "geocode": {
          "lat": 15.516798333333334,
          "lng": 74.92579833333333,
          "fix": 3
        }
      },
      {
        "geocode": {
          "lat": 15.51677,
          "lng": 74.92600166666666,
          "fix": 3
        }
      },
      {
        "geocode": {
          "lat": 15.516743333333334,
          "lng": 74.92620666666667,
          "fix": 3
        }
      },
      {
        "geocode": {
          "lat": 15.51672,
          "lng": 74.92641666666667,
          "fix": 3
        }
      }
    ],
    "multi_sp": [
      {
        "sp": 81.81
      },
      {
        "sp": 81.29
      },
      {
        "sp": 80.27
      },
      {
        "sp": 80.16
      },
      {
        "sp": 80.48
      },
      {
        "sp": 79.83
      },
      {
        "sp": 80.42
      },
      {
        "sp": 80.35
      },
      {
        "sp": 80.22
      },
      {
        "sp": 80.78
      }
    ],
    "loc": {
      "type": "Point",
      "coordinates": [
        15.51672,
        74.92641666666667
      ]
    },
    "fix": 3
  },
  {
    "_id": "158393297483727762:1496601116000",
    "refid": "726c428e-c967-48f6-b5c1-174134c42993",
    "timestamp": 1496601116000,
    "tracker_id": "151704003336602618",
    "vehicle_id": "158393297483727762",
    "sp": 82.2,
    "hd": 98.43,
    "exb": 1,
    "account_id": "149089795410363018",
    "battery": 100,
    "battery_str": 0,
    "dist_sp": 229.686096,
    "multi_geo": [
      {
        "geocode": {
          "lat": 15.516661666666666,
          "lng": 74.92683666666667,
          "fix": 3
        }
      },
      {
        "geocode": {
          "lat": 15.516633333333333,
          "lng": 74.92704666666667,
          "fix": 3
        }
      },
      {
        "geocode": {
          "lat": 15.516603333333334,
          "lng": 74.92725833333333,
          "fix": 3
        }
      },
      {
        "geocode": {
          "lat": 15.516573333333334,
          "lng": 74.92747,
          "fix": 3
        }
      },
      {
        "geocode": {
          "lat": 15.516543333333333,
          "lng": 74.92768333333333,
          "fix": 3
        }
      },
      {
        "geocode": {
          "lat": 15.516515,
          "lng": 74.927895,
          "fix": 3
        }
      },
      {
        "geocode": {
          "lat": 15.516485,
          "lng": 74.92810833333333,
          "fix": 3
        }
      },
      {
        "geocode": {
          "lat": 15.516455,
          "lng": 74.92832,
          "fix": 3
        }
      },
      {
        "geocode": {
          "lat": 15.516425,
          "lng": 74.92853166666667,
          "fix": 3
        }
      },
      {
        "geocode": {
          "lat": 15.516395,
          "lng": 74.92874166666667,
          "fix": 3
        }
      }
    ],
    "multi_sp": [
      {
        "sp": 81.74
      },
      {
        "sp": 82.06
      },
      {
        "sp": 82.47
      },
      {
        "sp": 82.93
      },
      {
        "sp": 83.54
      },
      {
        "sp": 83.43
      },
      {
        "sp": 82.76
      },
      {
        "sp": 82.9
      },
      {
        "sp": 82.84
      },
      {
        "sp": 82.2
      }
    ],
    "loc": {
      "type": "Point",
      "coordinates": [
        15.516395,
        74.92874166666667
      ]
    },
    "fix": 3
  },
  {
    "_id": "158393297483727762:1496601127000",
    "refid": "8c3bd2cd-43a5-425d-bb0c-39197f129f92",
    "timestamp": 1496601127000,
    "tracker_id": "151704003336602618",
    "vehicle_id": "158393297483727762",
    "sp": 85.79,
    "hd": 99.28,
    "exb": 1,
    "account_id": "149089795410363018",
    "battery": 100,
    "battery_str": 0,
    "dist_sp": 232.65834,
    "multi_geo": [
      {
        "geocode": {
          "lat": 15.516365,
          "lng": 74.92895333333334,
          "fix": 3
        }
      },
      {
        "geocode": {
          "lat": 15.516303333333333,
          "lng": 74.92937166666667,
          "fix": 3
        }
      },
      {
        "geocode": {
          "lat": 15.516275,
          "lng": 74.929585,
          "fix": 3
        }
      },
      {
        "geocode": {
          "lat": 15.516243333333334,
          "lng": 74.92979833333334,
          "fix": 3
        }
      },
      {
        "geocode": {
          "lat": 15.516211666666667,
          "lng": 74.93001,
          "fix": 3
        }
      },
      {
        "geocode": {
          "lat": 15.51618,
          "lng": 74.93022333333333,
          "fix": 3
        }
      },
      {
        "geocode": {
          "lat": 15.51615,
          "lng": 74.93044,
          "fix": 3
        }
      },
      {
        "geocode": {
          "lat": 15.516118333333333,
          "lng": 74.93065833333333,
          "fix": 3
        }
      },
      {
        "geocode": {
          "lat": 15.516085,
          "lng": 74.93087666666666,
          "fix": 3
        }
      },
      {
        "geocode": {
          "lat": 15.516056666666667,
          "lng": 74.93110333333334,
          "fix": 3
        }
      }
    ],
    "multi_sp": [
      {
        "sp": 82.2
      },
      {
        "sp": 81.89
      },
      {
        "sp": 83.1
      },
      {
        "sp": 83.45
      },
      {
        "sp": 83.47
      },
      {
        "sp": 83.93
      },
      {
        "sp": 84.33
      },
      {
        "sp": 84.33
      },
      {
        "sp": 85.08
      },
      {
        "sp": 85.79
      }
    ],
    "loc": {
      "type": "Point",
      "coordinates": [
        15.516056666666667,
        74.93110333333334
      ]
    },
    "fix": 3
  },
  {
    "_id": "158393297483727762:1496601138000",
    "refid": "5b31a56c-ad38-4d79-80d5-11fd8525d6fe",
    "timestamp": 1496601138000,
    "tracker_id": "151704003336602618",
    "vehicle_id": "158393297483727762",
    "sp": 85.01,
    "hd": 110.72,
    "exb": 1,
    "account_id": "149089795410363018",
    "battery": 100,
    "battery_str": 0,
    "dist_sp": 234.247253,
    "multi_geo": [
      {
        "geocode": {
          "lat": 15.51603,
          "lng": 74.93133166666667,
          "fix": 3
        }
      },
      {
        "geocode": {
          "lat": 15.515966666666667,
          "lng": 74.93177333333334,
          "fix": 3
        }
      },
      {
        "geocode": {
          "lat": 15.515938333333333,
          "lng": 74.93199,
          "fix": 3
        }
      },
      {
        "geocode": {
          "lat": 15.515901666666666,
          "lng": 74.932195,
          "fix": 3
        }
      },
      {
        "geocode": {
          "lat": 15.515865,
          "lng": 74.9324,
          "fix": 3
        }
      },
      {
        "geocode": {
          "lat": 15.515821666666668,
          "lng": 74.93261,
          "fix": 3
        }
      },
      {
        "geocode": {
          "lat": 15.515773333333334,
          "lng": 74.93281833333333,
          "fix": 3
        }
      },
      {
        "geocode": {
          "lat": 15.51571,
          "lng": 74.93302166666666,
          "fix": 3
        }
      },
      {
        "geocode": {
          "lat": 15.515633333333334,
          "lng": 74.93321833333333,
          "fix": 3
        }
      },
      {
        "geocode": {
          "lat": 15.515556666666667,
          "lng": 74.93341833333334,
          "fix": 3
        }
      }
    ],
    "multi_sp": [
      {
        "sp": 86.2
      },
      {
        "sp": 84.97
      },
      {
        "sp": 84.38
      },
      {
        "sp": 84.34
      },
      {
        "sp": 83.42
      },
      {
        "sp": 83.41
      },
      {
        "sp": 83.37
      },
      {
        "sp": 84.11
      },
      {
        "sp": 84.08
      },
      {
        "sp": 85.01
      }
    ],
    "loc": {
      "type": "Point",
      "coordinates": [
        15.515556666666667,
        74.93341833333334
      ]
    },
    "fix": 3
  },
  {
    "_id": "158393297483727762:1496601149000",
    "refid": "042ff3b9-074e-4078-a588-736ee2a6f436",
    "timestamp": 1496601149000,
    "tracker_id": "151704003336602618",
    "vehicle_id": "158393297483727762",
    "sp": 96.86,
    "hd": 111.87,
    "exb": 1,
    "account_id": "149089795410363018",
    "battery": 100,
    "battery_str": 0,
    "dist_sp": 255.402771,
    "multi_geo": [
      {
        "geocode": {
          "lat": 15.515476666666666,
          "lng": 74.93361833333333,
          "fix": 3
        }
      },
      {
        "geocode": {
          "lat": 15.515308333333333,
          "lng": 74.93402666666667,
          "fix": 3
        }
      },
      {
        "geocode": {
          "lat": 15.515225,
          "lng": 74.93424,
          "fix": 3
        }
      },
      {
        "geocode": {
          "lat": 15.515141666666667,
          "lng": 74.934455,
          "fix": 3
        }
      },
      {
        "geocode": {
          "lat": 15.515056666666666,
          "lng": 74.934675,
          "fix": 3
        }
      },
      {
        "geocode": {
          "lat": 15.514971666666666,
          "lng": 74.93489833333334,
          "fix": 3
        }
      },
      {
        "geocode": {
          "lat": 15.514885,
          "lng": 74.93512666666666,
          "fix": 3
        }
      },
      {
        "geocode": {
          "lat": 15.514795,
          "lng": 74.93536,
          "fix": 3
        }
      },
      {
        "geocode": {
          "lat": 15.514703333333333,
          "lng": 74.93559333333333,
          "fix": 3
        }
      },
      {
        "geocode": {
          "lat": 15.51461,
          "lng": 74.935825,
          "fix": 3
        }
      }
    ],
    "multi_sp": [
      {
        "sp": 85.11
      },
      {
        "sp": 87.44
      },
      {
        "sp": 89.64
      },
      {
        "sp": 90.32
      },
      {
        "sp": 91.33
      },
      {
        "sp": 93.25
      },
      {
        "sp": 94.07
      },
      {
        "sp": 95.65
      },
      {
        "sp": 95.78
      },
      {
        "sp": 96.86
      }
    ],
    "loc": {
      "type": "Point",
      "coordinates": [
        15.51461,
        74.935825
      ]
    },
    "fix": 3
  },
  {
    "_id": "158393297483727762:1496601160000",
    "refid": "cae2f13e-13b5-40e9-aad7-6abc3e357871",
    "timestamp": 1496601160000,
    "tracker_id": "151704003336602618",
    "vehicle_id": "158393297483727762",
    "sp": 97.97,
    "hd": 111.74,
    "exb": 1,
    "account_id": "149089795410363018",
    "battery": 100,
    "battery_str": 0,
    "dist_sp": 268.447235,
    "multi_geo": [
      {
        "geocode": {
          "lat": 15.514516666666667,
          "lng": 74.93605833333334,
          "fix": 3
        }
      },
      {
        "geocode": {
          "lat": 15.51433,
          "lng": 74.93652833333333,
          "fix": 3
        }
      },
      {
        "geocode": {
          "lat": 15.514238333333333,
          "lng": 74.93676,
          "fix": 3
        }
      },
      {
        "geocode": {
          "lat": 15.514148333333333,
          "lng": 74.93698666666667,
          "fix": 3
        }
      },
      {
        "geocode": {
          "lat": 15.514058333333333,
          "lng": 74.93721166666667,
          "fix": 3
        }
      },
      {
        "geocode": {
          "lat": 15.51397,
          "lng": 74.93744166666667,
          "fix": 3
        }
      },
      {
        "geocode": {
          "lat": 15.51388,
          "lng": 74.93767,
          "fix": 3
        }
      },
      {
        "geocode": {
          "lat": 15.513786666666666,
          "lng": 74.9379,
          "fix": 3
        }
      },
      {
        "geocode": {
          "lat": 15.513695,
          "lng": 74.93812666666666,
          "fix": 3
        }
      },
      {
        "geocode": {
          "lat": 15.513605,
          "lng": 74.93836,
          "fix": 3
        }
      }
    ],
    "multi_sp": [
      {
        "sp": 97.85
      },
      {
        "sp": 96.49
      },
      {
        "sp": 96.11
      },
      {
        "sp": 95.79
      },
      {
        "sp": 95.18
      },
      {
        "sp": 96.46
      },
      {
        "sp": 96.55
      },
      {
        "sp": 96.95
      },
      {
        "sp": 97.06
      },
      {
        "sp": 97.97
      }
    ],
    "loc": {
      "type": "Point",
      "coordinates": [
        15.513605,
        74.93836
      ]
    },
    "fix": 3
  },
  {
    "_id": "158393297483727762:1496601172000",
    "refid": "e0683c18-928b-48a8-b083-1918837b2584",
    "timestamp": 1496601172000,
    "tracker_id": "151704003336602618",
    "vehicle_id": "158393297483727762",
    "sp": 100.71,
    "hd": 111.12,
    "exb": 1,
    "account_id": "149089795410363018",
    "battery": 100,
    "battery_str": 0,
    "dist_sp": 274.897217,
    "multi_geo": [
      {
        "geocode": {
          "lat": 15.513513333333334,
          "lng": 74.93859666666667,
          "fix": 3
        }
      },
      {
        "geocode": {
          "lat": 15.513245,
          "lng": 74.93929666666666,
          "fix": 3
        }
      },
      {
        "geocode": {
          "lat": 15.513155,
          "lng": 74.93953333333333,
          "fix": 3
        }
      },
      {
        "geocode": {
          "lat": 15.513065,
          "lng": 74.93977,
          "fix": 3
        }
      },
      {
        "geocode": {
          "lat": 15.512975,
          "lng": 74.94000333333334,
          "fix": 3
        }
      },
      {
        "geocode": {
          "lat": 15.512885,
          "lng": 74.94023833333333,
          "fix": 3
        }
      },
      {
        "geocode": {
          "lat": 15.512793333333333,
          "lng": 74.94047166666667,
          "fix": 3
        }
      },
      {
        "geocode": {
          "lat": 15.512703333333333,
          "lng": 74.94071166666667,
          "fix": 3
        }
      },
      {
        "geocode": {
          "lat": 15.512611666666666,
          "lng": 74.94095,
          "fix": 3
        }
      },
      {
        "geocode": {
          "lat": 15.512518333333333,
          "lng": 74.94119166666667,
          "fix": 3
        }
      }
    ],
    "multi_sp": [
      {
        "sp": 98.62
      },
      {
        "sp": 98.48
      },
      {
        "sp": 98.5
      },
      {
        "sp": 99.05
      },
      {
        "sp": 98.52
      },
      {
        "sp": 97.61
      },
      {
        "sp": 98.73
      },
      {
        "sp": 99.49
      },
      {
        "sp": 99.92
      },
      {
        "sp": 100.71
      }
    ],
    "loc": {
      "type": "Point",
      "coordinates": [
        15.512518333333333,
        74.94119166666667
      ]
    },
    "fix": 3
  },
  {
    "_id": "158393297483727762:1496601183000",
    "refid": "fa78a9f8-aad2-415d-9143-4b185f44cacb",
    "timestamp": 1496601183000,
    "tracker_id": "151704003336602618",
    "vehicle_id": "158393297483727762",
    "sp": 92.69,
    "hd": 116.37,
    "exb": 1,
    "account_id": "149089795410363018",
    "battery": 100,
    "battery_str": 0,
    "dist_sp": 269.799988,
    "multi_geo": [
      {
        "geocode": {
          "lat": 15.512423333333333,
          "lng": 74.94143333333334,
          "fix": 3
        }
      },
      {
        "geocode": {
          "lat": 15.512231666666667,
          "lng": 74.94191666666667,
          "fix": 3
        }
      },
      {
        "geocode": {
          "lat": 15.512138333333333,
          "lng": 74.94215333333334,
          "fix": 3
        }
      },
      {
        "geocode": {
          "lat": 15.512045,
          "lng": 74.94239,
          "fix": 3
        }
      },
      {
        "geocode": {
          "lat": 15.511953333333333,
          "lng": 74.942625,
          "fix": 3
        }
      },
      {
        "geocode": {
          "lat": 15.511861666666666,
          "lng": 74.94286,
          "fix": 3
        }
      },
      {
        "geocode": {
          "lat": 15.511768333333332,
          "lng": 74.94309166666666,
          "fix": 3
        }
      },
      {
        "geocode": {
          "lat": 15.511673333333333,
          "lng": 74.94331833333334,
          "fix": 3
        }
      },
      {
        "geocode": {
          "lat": 15.511575,
          "lng": 74.94354166666666,
          "fix": 3
        }
      },
      {
        "geocode": {
          "lat": 15.511471666666667,
          "lng": 74.94376,
          "fix": 3
        }
      }
    ],
    "multi_sp": [
      {
        "sp": 101.63
      },
      {
        "sp": 99.24
      },
      {
        "sp": 99.15
      },
      {
        "sp": 99.03
      },
      {
        "sp": 98.24
      },
      {
        "sp": 97.5
      },
      {
        "sp": 96.09
      },
      {
        "sp": 94.2
      },
      {
        "sp": 93.51
      },
      {
        "sp": 92.69
      }
    ],
    "loc": {
      "type": "Point",
      "coordinates": [
        15.511471666666667,
        74.94376
      ]
    },
    "fix": 3
  },
  {
    "_id": "158393297483727762:1496601194000",
    "refid": "3cfa6e9c-c4e1-4d10-afb9-696f2a448c50",
    "timestamp": 1496601194000,
    "tracker_id": "151704003336602618",
    "vehicle_id": "158393297483727762",
    "sp": 89.1,
    "hd": 139.46,
    "exb": 1,
    "account_id": "149089795410363018",
    "battery": 100,
    "battery_str": 0,
    "dist_sp": 252.555557,
    "multi_geo": [
      {
        "geocode": {
          "lat": 15.511361666666666,
          "lng": 74.943975,
          "fix": 3
        }
      },
      {
        "geocode": {
          "lat": 15.511125,
          "lng": 74.94438166666667,
          "fix": 3
        }
      },
      {
        "geocode": {
          "lat": 15.510993333333333,
          "lng": 74.94457333333334,
          "fix": 3
        }
      },
      {
        "geocode": {
          "lat": 15.510848333333334,
          "lng": 74.94475833333334,
          "fix": 3
        }
      },
      {
        "geocode": {
          "lat": 15.510701666666666,
          "lng": 74.944945,
          "fix": 3
        }
      },
      {
        "geocode": {
          "lat": 15.510548333333332,
          "lng": 74.94511833333334,
          "fix": 3
        }
      },
      {
        "geocode": {
          "lat": 15.5104,
          "lng": 74.945285,
          "fix": 3
        }
      },
      {
        "geocode": {
          "lat": 15.510238333333334,
          "lng": 74.94544833333333,
          "fix": 3
        }
      },
      {
        "geocode": {
          "lat": 15.510071666666667,
          "lng": 74.945605,
          "fix": 3
        }
      },
      {
        "geocode": {
          "lat": 15.509901666666666,
          "lng": 74.94574666666666,
          "fix": 3
        }
      }
    ],
    "multi_sp": [
      {
        "sp": 92.79
      },
      {
        "sp": 90.7
      },
      {
        "sp": 91.29
      },
      {
        "sp": 92.43
      },
      {
        "sp": 90.88
      },
      {
        "sp": 90.94
      },
      {
        "sp": 90.91
      },
      {
        "sp": 90.37
      },
      {
        "sp": 89.79
      },
      {
        "sp": 89.1
      }
    ],
    "loc": {
      "type": "Point",
      "coordinates": [
        15.509901666666666,
        74.94574666666666
      ]
    },
    "fix": 3
  },
  {
    "_id": "158393297483727762:1496601206000",
    "refid": "6fe06a97-4632-449c-bc99-5fc4b99c8f40",
    "timestamp": 1496601206000,
    "tracker_id": "151704003336602618",
    "vehicle_id": "158393297483727762",
    "sp": 86.01,
    "hd": 142.24,
    "exb": 1,
    "account_id": "149089795410363018",
    "battery": 100,
    "battery_str": 0,
    "dist_sp": 239.19722,
    "multi_geo": [
      {
        "geocode": {
          "lat": 15.509726666666667,
          "lng": 74.94588833333333,
          "fix": 3
        }
      },
      {
        "geocode": {
          "lat": 15.509376666666666,
          "lng": 74.94615666666667,
          "fix": 3
        }
      },
      {
        "geocode": {
          "lat": 15.509203333333334,
          "lng": 74.946285,
          "fix": 3
        }
      },
      {
        "geocode": {
          "lat": 15.509031666666667,
          "lng": 74.946415,
          "fix": 3
        }
      },
      {
        "geocode": {
          "lat": 15.50886,
          "lng": 74.94654833333334,
          "fix": 3
        }
      },
      {
        "geocode": {
          "lat": 15.508686666666666,
          "lng": 74.94668166666666,
          "fix": 3
        }
      },
      {
        "geocode": {
          "lat": 15.508518333333333,
          "lng": 74.94681333333334,
          "fix": 3
        }
      },
      {
        "geocode": {
          "lat": 15.508346666666666,
          "lng": 74.94694833333334,
          "fix": 3
        }
      },
      {
        "geocode": {
          "lat": 15.508178333333333,
          "lng": 74.94707833333334,
          "fix": 3
        }
      },
      {
        "geocode": {
          "lat": 15.507838333333334,
          "lng": 74.947345,
          "fix": 3
        }
      }
    ],
    "multi_sp": [
      {
        "sp": 88.54
      },
      {
        "sp": 88.08
      },
      {
        "sp": 86.75
      },
      {
        "sp": 86.06
      },
      {
        "sp": 85.7
      },
      {
        "sp": 85.68
      },
      {
        "sp": 84.5
      },
      {
        "sp": 85.09
      },
      {
        "sp": 84.7
      },
      {
        "sp": 86.01
      }
    ],
    "loc": {
      "type": "Point",
      "coordinates": [
        15.507838333333334,
        74.947345
      ]
    },
    "fix": 3
  },
  {
    "_id": "158393297483727762:1496601217000",
    "refid": "4f3a835a-f4b3-4554-99e7-cc8c15c3f412",
    "timestamp": 1496601217000,
    "tracker_id": "151704003336602618",
    "vehicle_id": "158393297483727762",
    "sp": 82.62,
    "hd": 137.03,
    "exb": 1,
    "account_id": "149089795410363018",
    "battery": 100,
    "battery_str": 0,
    "dist_sp": 237.955551,
    "multi_geo": [
      {
        "geocode": {
          "lat": 15.507666666666667,
          "lng": 74.947475,
          "fix": 3
        }
      },
      {
        "geocode": {
          "lat": 15.507325,
          "lng": 74.94775166666666,
          "fix": 3
        }
      },
      {
        "geocode": {
          "lat": 15.507153333333333,
          "lng": 74.94789166666666,
          "fix": 3
        }
      },
      {
        "geocode": {
          "lat": 15.506981666666666,
          "lng": 74.94803166666667,
          "fix": 3
        }
      },
      {
        "geocode": {
          "lat": 15.506813333333334,
          "lng": 74.948175,
          "fix": 3
        }
      },
      {
        "geocode": {
          "lat": 15.506646666666667,
          "lng": 74.94832,
          "fix": 3
        }
      },
      {
        "geocode": {
          "lat": 15.506483333333334,
          "lng": 74.94846833333334,
          "fix": 3
        }
      },
      {
        "geocode": {
          "lat": 15.506321666666667,
          "lng": 74.94862,
          "fix": 3
        }
      },
      {
        "geocode": {
          "lat": 15.506163333333333,
          "lng": 74.94877,
          "fix": 3
        }
      },
      {
        "geocode": {
          "lat": 15.506008333333334,
          "lng": 74.94891666666666,
          "fix": 3
        }
      }
    ],
    "multi_sp": [
      {
        "sp": 86.07
      },
      {
        "sp": 86.07
      },
      {
        "sp": 86.81
      },
      {
        "sp": 87.41
      },
      {
        "sp": 86.2
      },
      {
        "sp": 86.25
      },
      {
        "sp": 86.24
      },
      {
        "sp": 85.28
      },
      {
        "sp": 83.69
      },
      {
        "sp": 82.62
      }
    ],
    "loc": {
      "type": "Point",
      "coordinates": [
        15.506008333333334,
        74.94891666666666
      ]
    },
    "fix": 3
  },
  {
    "_id": "158393297483727762:1496601228000",
    "refid": "3279dd06-54b6-40cf-a0da-e67741a34d92",
    "timestamp": 1496601228000,
    "tracker_id": "151704003336602618",
    "vehicle_id": "158393297483727762",
    "sp": 87.98,
    "hd": 130.71,
    "exb": 1,
    "account_id": "149089795410363018",
    "battery": 100,
    "battery_str": 0,
    "dist_sp": 232.252777,
    "multi_geo": [
      {
        "geocode": {
          "lat": 15.50586,
          "lng": 74.94906666666667,
          "fix": 3
        }
      },
      {
        "geocode": {
          "lat": 15.505571666666667,
          "lng": 74.94937166666666,
          "fix": 3
        }
      },
      {
        "geocode": {
          "lat": 15.505426666666667,
          "lng": 74.94952333333333,
          "fix": 3
        }
      },
      {
        "geocode": {
          "lat": 15.505283333333333,
          "lng": 74.94967666666666,
          "fix": 3
        }
      },
      {
        "geocode": {
          "lat": 15.505143333333333,
          "lng": 74.94983166666667,
          "fix": 3
        }
      },
      {
        "geocode": {
          "lat": 15.505003333333333,
          "lng": 74.94999333333334,
          "fix": 3
        }
      },
      {
        "geocode": {
          "lat": 15.504863333333333,
          "lng": 74.95015666666667,
          "fix": 3
        }
      },
      {
        "geocode": {
          "lat": 15.504721666666667,
          "lng": 74.95032166666667,
          "fix": 3
        }
      },
      {
        "geocode": {
          "lat": 15.504578333333333,
          "lng": 74.95049166666666,
          "fix": 3
        }
      },
      {
        "geocode": {
          "lat": 15.504433333333333,
          "lng": 74.950665,
          "fix": 3
        }
      }
    ],
    "multi_sp": [
      {
        "sp": 81.87
      },
      {
        "sp": 80.89
      },
      {
        "sp": 81.37
      },
      {
        "sp": 81.86
      },
      {
        "sp": 82.3
      },
      {
        "sp": 83.44
      },
      {
        "sp": 84.39
      },
      {
        "sp": 85.05
      },
      {
        "sp": 86.96
      },
      {
        "sp": 87.98
      }
    ],
    "loc": {
      "type": "Point",
      "coordinates": [
        15.504433333333333,
        74.950665
      ]
    },
    "fix": 3
  },
  {
    "_id": "158393297483727762:1496601233000",
    "refid": "5b2d66df-5e26-46af-9b48-93d9a1e3cde3",
    "timestamp": 1496601233000,
    "tracker_id": "151704003336602618",
    "vehicle_id": "158393297483727762",
    "sp": 92.56,
    "account_id": "149089795410363018",
    "loc": {
      "type": "Point",
      "coordinates": [
        15.503681666666667,
        74.95155666666666
      ]
    },
    "fix": 3
  },
  {
    "_id": "158393297483727762:1496601239000",
    "refid": "d14f4d15-330c-479f-ab5f-442530c85029",
    "timestamp": 1496601239000,
    "tracker_id": "151704003336602618",
    "vehicle_id": "158393297483727762",
    "sp": 90.85,
    "hd": 130.96,
    "exb": 1,
    "account_id": "149089795410363018",
    "battery": 100,
    "battery_str": 0,
    "dist_sp": 253.5,
    "multi_geo": [
      {
        "geocode": {
          "lat": 15.504285,
          "lng": 74.95084,
          "fix": 3
        }
      },
      {
        "geocode": {
          "lat": 15.503983333333334,
          "lng": 74.95119333333334,
          "fix": 3
        }
      },
      {
        "geocode": {
          "lat": 15.503833333333333,
          "lng": 74.951375,
          "fix": 3
        }
      },
      {
        "geocode": {
          "lat": 15.503681666666667,
          "lng": 74.95155666666666,
          "fix": 3
        }
      },
      {
        "geocode": {
          "lat": 15.50353,
          "lng": 74.95173833333334,
          "fix": 3
        }
      },
      {
        "geocode": {
          "lat": 15.503378333333334,
          "lng": 74.95191666666666,
          "fix": 3
        }
      },
      {
        "geocode": {
          "lat": 15.50323,
          "lng": 74.95209666666666,
          "fix": 3
        }
      },
      {
        "geocode": {
          "lat": 15.503081666666667,
          "lng": 74.95227833333334,
          "fix": 3
        }
      },
      {
        "geocode": {
          "lat": 15.502933333333333,
          "lng": 74.952455,
          "fix": 3
        }
      },
      {
        "geocode": {
          "lat": 15.502785,
          "lng": 74.95263166666666,
          "fix": 3
        }
      }
    ],
    "multi_sp": [
      {
        "sp": 89.53
      },
      {
        "sp": 91.58
      },
      {
        "sp": 92.63
      },
      {
        "sp": 92.56
      },
      {
        "sp": 92.48
      },
      {
        "sp": 91.44
      },
      {
        "sp": 90.96
      },
      {
        "sp": 90.23
      },
      {
        "sp": 90.34
      },
      {
        "sp": 90.85
      }
    ],
    "loc": {
      "type": "Point",
      "coordinates": [
        15.502785,
        74.95263166666666
      ]
    },
    "fix": 3
  },
  {
    "_id": "158393297483727762:1496601250000",
    "refid": "eeed35f2-bf44-4d9f-9752-b0817e3bf7ff",
    "timestamp": 1496601250000,
    "tracker_id": "151704003336602618",
    "vehicle_id": "158393297483727762",
    "sp": 89.27,
    "hd": 130.36,
    "exb": 1,
    "account_id": "149089795410363018",
    "battery": 100,
    "battery_str": 0,
    "dist_sp": 254.024994,
    "multi_geo": [
      {
        "geocode": {
          "lat": 15.502635,
          "lng": 74.952805,
          "fix": 3
        }
      },
      {
        "geocode": {
          "lat": 15.502335,
          "lng": 74.95315666666667,
          "fix": 3
        }
      },
      {
        "geocode": {
          "lat": 15.502183333333333,
          "lng": 74.95333333333333,
          "fix": 3
        }
      },
      {
        "geocode": {
          "lat": 15.50203,
          "lng": 74.95351666666667,
          "fix": 3
        }
      },
      {
        "geocode": {
          "lat": 15.501881666666666,
          "lng": 74.95369833333334,
          "fix": 3
        }
      },
      {
        "geocode": {
          "lat": 15.501731666666666,
          "lng": 74.953875,
          "fix": 3
        }
      },
      {
        "geocode": {
          "lat": 15.50158,
          "lng": 74.95405333333333,
          "fix": 3
        }
      },
      {
        "geocode": {
          "lat": 15.501431666666667,
          "lng": 74.95422833333333,
          "fix": 3
        }
      },
      {
        "geocode": {
          "lat": 15.501283333333333,
          "lng": 74.9544,
          "fix": 3
        }
      },
      {
        "geocode": {
          "lat": 15.501136666666667,
          "lng": 74.95457166666667,
          "fix": 3
        }
      }
    ],
    "multi_sp": [
      {
        "sp": 90.49
      },
      {
        "sp": 91.29
      },
      {
        "sp": 91.84
      },
      {
        "sp": 93.31
      },
      {
        "sp": 92.9
      },
      {
        "sp": 92.17
      },
      {
        "sp": 91.6
      },
      {
        "sp": 91.16
      },
      {
        "sp": 90.46
      },
      {
        "sp": 89.27
      }
    ],
    "loc": {
      "type": "Point",
      "coordinates": [
        15.501136666666667,
        74.95457166666667
      ]
    },
    "fix": 3
  },
  {
    "_id": "158393297483727762:1496601261000",
    "refid": "62a00351-dec7-4628-9d00-f633ad4b09a9",
    "timestamp": 1496601261000,
    "tracker_id": "151704003336602618",
    "vehicle_id": "158393297483727762",
    "sp": 87.78,
    "hd": 125.52,
    "exb": 1,
    "account_id": "149089795410363018",
    "battery": 100,
    "battery_str": 0,
    "dist_sp": 243.449997,
    "multi_geo": [
      {
        "geocode": {
          "lat": 15.500991666666666,
          "lng": 74.95474833333333,
          "fix": 3
        }
      },
      {
        "geocode": {
          "lat": 15.5007,
          "lng": 74.95509666666666,
          "fix": 3
        }
      },
      {
        "geocode": {
          "lat": 15.500556666666666,
          "lng": 74.95527166666666,
          "fix": 3
        }
      },
      {
        "geocode": {
          "lat": 15.500413333333332,
          "lng": 74.955445,
          "fix": 3
        }
      },
      {
        "geocode": {
          "lat": 15.500268333333333,
          "lng": 74.95561666666667,
          "fix": 3
        }
      },
      {
        "geocode": {
          "lat": 15.500126666666667,
          "lng": 74.955785,
          "fix": 3
        }
      },
      {
        "geocode": {
          "lat": 15.499985,
          "lng": 74.95595833333333,
          "fix": 3
        }
      },
      {
        "geocode": {
          "lat": 15.499843333333333,
          "lng": 74.956135,
          "fix": 3
        }
      },
      {
        "geocode": {
          "lat": 15.49971,
          "lng": 74.956315,
          "fix": 3
        }
      },
      {
        "geocode": {
          "lat": 15.49958,
          "lng": 74.95650166666667,
          "fix": 3
        }
      }
    ],
    "multi_sp": [
      {
        "sp": 89.31
      },
      {
        "sp": 89
      },
      {
        "sp": 88.03
      },
      {
        "sp": 88.09
      },
      {
        "sp": 87.18
      },
      {
        "sp": 87.29
      },
      {
        "sp": 87.19
      },
      {
        "sp": 86.44
      },
      {
        "sp": 86.11
      },
      {
        "sp": 87.78
      }
    ],
    "loc": {
      "type": "Point",
      "coordinates": [
        15.49958,
        74.95650166666667
      ]
    },
    "fix": 3
  }
]